msmcauth/__init__.py
msmcauth/consts.py
msmcauth/errors.py
msmcauth/microsoft.py
msmcauth/types.py
msmcauth/xbox.py
msmcauth-0.0.4.dist-info/METADATA
msmcauth-0.0.4.dist-info/WHEEL
msmcauth-0.0.4.dist-info/top_level.txt
msmcauth-0.0.4.dist-info/RECORD
