Metadata-Version: 2.1
Name: msmcauth
Version: 0.0.4
Summary: Microsoft Minecraft Auth
Home-page: UNKNOWN
Author: Mohanad Hosny
License: UNKNOWN
Keywords: python,minecraft,microsoft,minecraft,auth
Platform: UNKNOWN
Classifier: Intended Audience :: Developers
Classifier: Programming Language :: Python :: 3
Classifier: Operating System :: Unix
Classifier: Operating System :: MacOS :: MacOS X
Classifier: Operating System :: Microsoft :: Windows
Requires-Dist: requests
